crondir/__init__.py
crondir/__main__.py
crondir/commands.py
crondir/crondir.py
crondir/exceptions.py
crondir/settings.py
crondir-0.3.0.dist-info/licenses/LICENSE
crondir-0.3.0.dist-info/METADATA
crondir-0.3.0.dist-info/WHEEL
crondir-0.3.0.dist-info/entry_points.txt
crondir-0.3.0.dist-info/top_level.txt
crondir-0.3.0.dist-info/RECORD
