Metadata-Version: 2.4
Name: crondir
Version: 0.3.0
Summary: A user-space cron.d directory
Author-email: Richard Terry <code@radiac.net>
License-Expression: BSD-3-Clause
Project-URL: Homepage, https://radiac.net/projects/crondir/
Project-URL: Documentation, https://github.com/radiac/crondir
Project-URL: Changelog, https://crondir.readthedocs.io/en/latest/changelog.html
Project-URL: Repository, https://github.com/radiac/crondir
Project-URL: Issues, https://github.com/radiac/crondir/issues
Classifier: Development Status :: 4 - Beta
Classifier: Programming Language :: Python :: 3
Classifier: Operating System :: OS Independent
Requires-Python: >=3.9
License-File: LICENSE
Requires-Dist: click
Dynamic: license-file
